image_processing_barbara/__init__.py
image_processing_barbara/processing/__init__.py
image_processing_barbara/processing/combination.py
image_processing_barbara/processing/transformation.py
image_processing_barbara/utils/__init__.py
image_processing_barbara/utils/io.py
image_processing_barbara/utils/plot.py
image_processing_barbara-0.0.1.dist-info/METADATA
image_processing_barbara-0.0.1.dist-info/WHEEL
image_processing_barbara-0.0.1.dist-info/top_level.txt
image_processing_barbara-0.0.1.dist-info/RECORD
