Metadata-Version: 2.1
Name: image-processing-barbara
Version: 0.0.1
Summary: This package is used to read, processing and plot images.
Home-page: https://github.com/barbaramir/bootcamp_unimedbh_ciencia_dados/tree/main/image_processing
Author: Karina
Author-email: name@email.com
Requires-Python: >=3.8
Requires-Dist: matplotlib
Requires-Dist: numpy
Requires-Dist: scikit-image (>=0.16.1)
